telethon/__init__.py
telethon/custom.py
telethon/functions.py
telethon/helpers.py
telethon/hints.py
telethon/password.py
telethon/requestiter.py
telethon/sync.py
telethon/types.py
telethon/utils.py
telethon/version.py
telethon/_updates/__init__.py
telethon/_updates/entitycache.py
telethon/_updates/messagebox.py
telethon/_updates/session.py
telethon/client/__init__.py
telethon/client/account.py
telethon/client/auth.py
telethon/client/bots.py
telethon/client/buttons.py
telethon/client/chats.py
telethon/client/dialogs.py
telethon/client/downloads.py
telethon/client/messageparse.py
telethon/client/messages.py
telethon/client/telegrambaseclient.py
telethon/client/telegramclient.py
telethon/client/updates.py
telethon/client/uploads.py
telethon/client/users.py
telethon/crypto/__init__.py
telethon/crypto/aes.py
telethon/crypto/aesctr.py
telethon/crypto/authkey.py
telethon/crypto/cdndecrypter.py
telethon/crypto/factorization.py
telethon/crypto/libssl.py
telethon/crypto/rsa.py
telethon/errors/__init__.py
telethon/errors/common.py
telethon/errors/rpcbaseerrors.py
telethon/errors/rpcerrorlist.py
telethon/events/__init__.py
telethon/events/album.py
telethon/events/callbackquery.py
telethon/events/chataction.py
telethon/events/common.py
telethon/events/inlinequery.py
telethon/events/messagedeleted.py
telethon/events/messageedited.py
telethon/events/messageread.py
telethon/events/newmessage.py
telethon/events/raw.py
telethon/events/userupdate.py
telethon/extensions/__init__.py
telethon/extensions/binaryreader.py
telethon/extensions/html.py
telethon/extensions/markdown.py
telethon/extensions/messagepacker.py
telethon/network/__init__.py
telethon/network/authenticator.py
telethon/network/mtprotoplainsender.py
telethon/network/mtprotosender.py
telethon/network/mtprotostate.py
telethon/network/requeststate.py
telethon/network/connection/__init__.py
telethon/network/connection/connection.py
telethon/network/connection/http.py
telethon/network/connection/tcpabridged.py
Telethon_Mod-1.33.1.dist-info/LICENSE
Telethon_Mod-1.33.1.dist-info/METADATA
Telethon_Mod-1.33.1.dist-info/WHEEL
Telethon_Mod-1.33.1.dist-info/top_level.txt
Telethon_Mod-1.33.1.dist-info/RECORD
